<?xml version="1.0" encoding="utf-8"?>
<!--
Automatically generated IO group description. Please do NOT modify!
-->
<SunriseIOGroupDescription xmlns:xsi="http://www.w3.org/2001/XMLSchema-instance" xmlns:xsd="http://www.w3.org/2001/XMLSchema" Version="1.0.0">
  <IOGroup DisplayName="ControlPanel" IconName="ControlPanel" SignalTypes="InOut" TemplateName="ControlPanel">
    <IOs>
      <DigitalIOItem Name="PLAY_BUTTON" DataType="BOOL" IOType="Input" UsedBitWidth="1" IsConnected="true">
        <Description />
      </DigitalIOItem>
      <DigitalIOItem Name="STOP_BUTTON" DataType="BOOL" IOType="Input" UsedBitWidth="1" IsConnected="true">
        <Description />
      </DigitalIOItem>
      <DigitalIOItem Name="KEY_SWITCH_0" DataType="BOOL" IOType="Input" UsedBitWidth="1" IsConnected="true">
        <Description />
      </DigitalIOItem>
      <DigitalIOItem Name="KEY_SWITCH_1" DataType="BOOL" IOType="Input" UsedBitWidth="1" IsConnected="true">
        <Description />
      </DigitalIOItem>
      <DigitalIOItem Name="KEY_SWITCH_2" DataType="BOOL" IOType="Input" UsedBitWidth="1" IsConnected="true">
        <Description />
      </DigitalIOItem>
      <DigitalIOItem Name="APP_GREEN" DataType="BOOL" IOType="Output" UsedBitWidth="1" IsConnected="true">
        <Description />
      </DigitalIOItem>
      <DigitalIOItem Name="APP_RED" DataType="BOOL" IOType="Output" UsedBitWidth="1" IsConnected="true">
        <Description />
      </DigitalIOItem>
      <DigitalIOItem Name="APP_BLUE" DataType="BOOL" IOType="Output" UsedBitWidth="1" IsConnected="true">
        <Description />
      </DigitalIOItem>
      <DigitalIOItem Name="SAFETY_BLUE" DataType="BOOL" IOType="Output" UsedBitWidth="1" IsConnected="true">
        <Description />
      </DigitalIOItem>
      <DigitalIOItem Name="SAFETY_RED" DataType="BOOL" IOType="Output" UsedBitWidth="1" IsConnected="true">
        <Description />
      </DigitalIOItem>
      <DigitalIOItem Name="SAFETY_GREEN" DataType="BOOL" IOType="Output" UsedBitWidth="1" IsConnected="true">
        <Description />
      </DigitalIOItem>
      <DigitalIOItem Name="DEVICE_BLUE" DataType="BOOL" IOType="Output" UsedBitWidth="1" IsConnected="true">
        <Description />
      </DigitalIOItem>
      <DigitalIOItem Name="DEVICE_RED" DataType="BOOL" IOType="Output" UsedBitWidth="1" IsConnected="true">
        <Description />
      </DigitalIOItem>
      <DigitalIOItem Name="DEVICE_GREEN" DataType="BOOL" IOType="Output" UsedBitWidth="1" IsConnected="true">
        <Description />
      </DigitalIOItem>
      <DigitalIOItem Name="BATTERY_GREEN" DataType="BOOL" IOType="Output" UsedBitWidth="1" IsConnected="true">
        <Description />
      </DigitalIOItem>
      <DigitalIOItem Name="BATTERY_RED" DataType="BOOL" IOType="Output" UsedBitWidth="1" IsConnected="true">
        <Description />
      </DigitalIOItem>
      <DigitalIOItem Name="BATTERY_BLUE" DataType="BOOL" IOType="Output" UsedBitWidth="1" IsConnected="true">
        <Description />
      </DigitalIOItem>
      <DigitalIOItem Name="PLAY_BUTTON_LED" DataType="BOOL" IOType="Output" UsedBitWidth="1" IsConnected="true">
        <Description />
      </DigitalIOItem>
      <DigitalIOItem Name="STOP_BUTTON_LED" DataType="BOOL" IOType="Output" UsedBitWidth="1" IsConnected="true">
        <Description />
      </DigitalIOItem>
      <DigitalIOItem Name="HONK" DataType="BOOL" IOType="Output" UsedBitWidth="1" IsConnected="true">
        <Description>Activates the vehicle honk</Description>
      </DigitalIOItem>
      <DigitalIOItem Name="SOCKET_CONNECTED" DataType="BOOL" IOType="Input" UsedBitWidth="1" IsConnected="true">
        <Description>True when the socket is connected.</Description>
      </DigitalIOItem>
    </IOs>
    <Description>Contains necessary information of the control panel (Buttons, Key-Switch, LED-States)</Description>
  </IOGroup>
</SunriseIOGroupDescription>